bagit_profile.py
ocrd_fork_bagit_profile-1.3.0.post1.data/scripts/bagit_profile.py
ocrd_fork_bagit_profile-1.3.0.post1.dist-info/LICENSE
ocrd_fork_bagit_profile-1.3.0.post1.dist-info/METADATA
ocrd_fork_bagit_profile-1.3.0.post1.dist-info/WHEEL
ocrd_fork_bagit_profile-1.3.0.post1.dist-info/top_level.txt
ocrd_fork_bagit_profile-1.3.0.post1.dist-info/RECORD
