Metadata-Version: 2.1
Name: ocrd-fork-bagit-profile
Version: 1.3.0.post1
Summary: This module can be used to validate BagitProfiles.
Home-page: https://github.com/bagit-profiles/bagit-profiles-validator
Author: Mark Jordan, Nick Ruest
Author-email: mjordan@sfu.ca, ruestn@gmail.com
License: CC0
Platform: POSIX
Classifier: License :: Public Domain
Classifier: Intended Audience :: Developers
Classifier: Topic :: Communications :: File Sharing
Classifier: Topic :: Software Development :: Libraries :: Python Modules
Classifier: Topic :: System :: Filesystems
Classifier: Topic :: Utilities
Classifier: Programming Language :: Python :: 2.7
Classifier: Programming Language :: Python :: 3.4
Classifier: Programming Language :: Python :: 3.5
Classifier: Programming Language :: Python :: 3.6
Classifier: Programming Language :: Python :: 3.7
License-File: LICENSE
